bvs/__init__.py
bvs/__main__.py
bvs/constant.py
bvs/crawler.py
bvs/mongo.py
bvs/parse_file.py
BvSalud-0.0.4.dist-info/LICENSE.txt
BvSalud-0.0.4.dist-info/METADATA
BvSalud-0.0.4.dist-info/WHEEL
BvSalud-0.0.4.dist-info/top_level.txt
BvSalud-0.0.4.dist-info/RECORD
